ros_rosidl_generator_c-4.9.5.data/data/lib/python3.13/site-packages/rosidl_generator_c/__init__.py
ros_rosidl_generator_c-4.9.5.data/data/lib/python3.13/site-packages/rosidl_generator_c/cli.py
ros_rosidl_generator_c-4.9.5.data/data/lib/python3.13/site-packages/rosidl_generator_c/__pycache__/__init__.cpython-313.pyc
ros_rosidl_generator_c-4.9.5.data/data/lib/python3.13/site-packages/rosidl_generator_c/__pycache__/cli.cpython-313.pyc
ros_rosidl_generator_c-4.9.5.data/data/lib/python3.13/site-packages/rosidl_generator_c-4.9.5-py3.13.egg-info/PKG-INFO
ros_rosidl_generator_c-4.9.5.data/data/lib/python3.13/site-packages/rosidl_generator_c-4.9.5-py3.13.egg-info/SOURCES.txt
ros_rosidl_generator_c-4.9.5.data/data/lib/python3.13/site-packages/rosidl_generator_c-4.9.5-py3.13.egg-info/dependency_links.txt
ros_rosidl_generator_c-4.9.5.data/data/lib/python3.13/site-packages/rosidl_generator_c-4.9.5-py3.13.egg-info/entry_points.txt
ros_rosidl_generator_c-4.9.5.data/data/lib/python3.13/site-packages/rosidl_generator_c-4.9.5-py3.13.egg-info/top_level.txt
ros_rosidl_generator_c-4.9.5.data/data/lib/rosidl_generator_c/rosidl_generator_c
ros_rosidl_generator_c-4.9.5.data/data/share/ament_index/resource_index/package_run_dependencies/rosidl_generator_c
ros_rosidl_generator_c-4.9.5.data/data/share/ament_index/resource_index/packages/rosidl_generator_c
ros_rosidl_generator_c-4.9.5.data/data/share/ament_index/resource_index/parent_prefix_path/rosidl_generator_c
ros_rosidl_generator_c-4.9.5.data/data/share/ament_index/resource_index/rosidl_generator_packages/rosidl_generator_c
ros_rosidl_generator_c-4.9.5.data/data/share/rosidl_generator_c/local_setup.bash
ros_rosidl_generator_c-4.9.5.data/data/share/rosidl_generator_c/local_setup.dsv
ros_rosidl_generator_c-4.9.5.data/data/share/rosidl_generator_c/local_setup.sh
ros_rosidl_generator_c-4.9.5.data/data/share/rosidl_generator_c/local_setup.zsh
ros_rosidl_generator_c-4.9.5.data/data/share/rosidl_generator_c/package.dsv
ros_rosidl_generator_c-4.9.5.data/data/share/rosidl_generator_c/package.xml
ros_rosidl_generator_c-4.9.5.data/data/share/rosidl_generator_c/cmake/ament_cmake_export_dependencies-extras.cmake
ros_rosidl_generator_c-4.9.5.data/data/share/rosidl_generator_c/cmake/register_c.cmake
ros_rosidl_generator_c-4.9.5.data/data/share/rosidl_generator_c/cmake/rosidl_generator_c-extras.cmake
ros_rosidl_generator_c-4.9.5.data/data/share/rosidl_generator_c/cmake/rosidl_generator_cConfig-version.cmake
ros_rosidl_generator_c-4.9.5.data/data/share/rosidl_generator_c/cmake/rosidl_generator_cConfig.cmake
ros_rosidl_generator_c-4.9.5.dist-info/METADATA
ros_rosidl_generator_c-4.9.5.dist-info/WHEEL
ros_rosidl_generator_c-4.9.5.dist-info/entry_points.txt
ros_rosidl_generator_c-4.9.5.dist-info/top_level.txt
ros_rosidl_generator_c-4.9.5.dist-info/RECORD
